galaxy/__init__.py
galaxy/app.py
galaxy/config_watchers.py
galaxy/di.py
galaxy/main.py
galaxy/main_config.py
galaxy/py.typed
galaxy/queue_worker.py
galaxy/queues.py
galaxy/structured_app.py
galaxy/actions/__init__.py
galaxy/actions/library.py
galaxy/app_unittest_utils/__init__.py
galaxy/app_unittest_utils/galaxy_mock.py
galaxy/app_unittest_utils/toolbox_support.py
galaxy/app_unittest_utils/tools_support.py
galaxy/authnz/__init__.py
galaxy/authnz/custos_authnz.py
galaxy/authnz/managers.py
galaxy/authnz/psa_authnz.py
galaxy/authnz/tapis.py
galaxy/authnz/util.py
galaxy/carbon_emissions/__init__.py
galaxy/carbon_emissions/carbon_intensity.csv
galaxy/celery/__init__.py
galaxy/celery/_serialization.py
galaxy/celery/base_task.py
galaxy/celery/tasks.py
galaxy/dependencies/__init__.py
galaxy/dependencies/conditional-requirements.txt
galaxy/dependencies/dev-requirements.txt
galaxy/dependencies/lint-requirements.txt
galaxy/dependencies/pinned-lint-requirements.txt
galaxy/dependencies/pinned-requirements.txt
galaxy/dependencies/pinned-typecheck-requirements.txt
galaxy/dependencies/script.py
galaxy/dependencies/update.sh
galaxy/dependencies/update_lint_requirements.sh
galaxy/forms/__init__.py
galaxy/forms/forms.py
galaxy/jobs/__init__.py
galaxy/jobs/command_factory.py
galaxy/jobs/dynamic_tool_destination.py
galaxy/jobs/handler.py
galaxy/jobs/manager.py
galaxy/jobs/mapper.py
galaxy/jobs/rule_helper.py
galaxy/jobs/stock_rules.py
galaxy/jobs/rules/__init__.py
galaxy/jobs/runners/__init__.py
galaxy/jobs/runners/aws.py
galaxy/jobs/runners/chronos.py
galaxy/jobs/runners/cli.py
galaxy/jobs/runners/condor.py
galaxy/jobs/runners/drmaa.py
galaxy/jobs/runners/godocker.py
galaxy/jobs/runners/kubernetes.py
galaxy/jobs/runners/local.py
galaxy/jobs/runners/pbs.py
galaxy/jobs/runners/pulsar.py
galaxy/jobs/runners/slurm.py
galaxy/jobs/runners/state_handler_factory.py
galaxy/jobs/runners/tasks.py
galaxy/jobs/runners/univa.py
galaxy/jobs/runners/state_handlers/__init__.py
galaxy_app-25.0.3.dist-info/licenses/LICENSE
galaxy_app-25.0.3.dist-info/METADATA
galaxy_app-25.0.3.dist-info/WHEEL
galaxy_app-25.0.3.dist-info/entry_points.txt
galaxy_app-25.0.3.dist-info/top_level.txt
galaxy_app-25.0.3.dist-info/RECORD
