Metadata-Version: 2.4
Name: galaxy-app
Version: 25.0.3
Summary: Galaxy application (backend)
Home-page: https://github.com/galaxyproject/galaxy
Author: Galaxy Project and Community
Author-email: galaxy-committers@lists.galaxyproject.org
License: AFL
Keywords: Galaxy
Classifier: Development Status :: 5 - Production/Stable
Classifier: Environment :: Console
Classifier: Intended Audience :: Developers
Classifier: License :: OSI Approved :: Academic Free License (AFL)
Classifier: Natural Language :: English
Classifier: Operating System :: POSIX
Classifier: Programming Language :: Python :: 3
Classifier: Programming Language :: Python :: 3.9
Classifier: Programming Language :: Python :: 3.10
Classifier: Programming Language :: Python :: 3.11
Classifier: Programming Language :: Python :: 3.12
Classifier: Programming Language :: Python :: 3.13
Classifier: Topic :: Software Development
Classifier: Topic :: Software Development :: Code Generators
Classifier: Topic :: Software Development :: Testing
Requires-Python: >=3.9
License-File: LICENSE
Requires-Dist: galaxy-auth
Requires-Dist: galaxy-config
Requires-Dist: galaxy-data
Requires-Dist: galaxy-files
Requires-Dist: galaxy-job-execution
Requires-Dist: galaxy-job-metrics
Requires-Dist: galaxy-objectstore
Requires-Dist: galaxy-tool-util[cwl,edam]
Requires-Dist: galaxy-tool-shed-schema
Requires-Dist: galaxy-tours
Requires-Dist: galaxy-util[image-util]
Requires-Dist: galaxy-web-framework
Requires-Dist: galaxy-web-stack
Requires-Dist: Beaker
Requires-Dist: boltons
Requires-Dist: bx-python
Requires-Dist: celery
Requires-Dist: cloudauthz==0.6.0
Requires-Dist: cwl-utils
Requires-Dist: dparse
Requires-Dist: gxformat2
Requires-Dist: kombu>=5.3
Requires-Dist: lagom
Requires-Dist: lxml!=4.2.2
Requires-Dist: Mako
Requires-Dist: Markdown
Requires-Dist: MarkupSafe
Requires-Dist: mercurial>=6.8.2
Requires-Dist: packaging
Requires-Dist: paramiko!=2.9.0,!=2.9.1
Requires-Dist: pebble
Requires-Dist: pulsar-galaxy-lib>=0.15.0.dev0
Requires-Dist: pydantic>=2.7.4
Requires-Dist: pysam>=0.21
Requires-Dist: python-slugify
Requires-Dist: PyJWT
Requires-Dist: PyYAML
Requires-Dist: refgenconf>=0.12.0
Requires-Dist: regex
Requires-Dist: requests
Requires-Dist: SQLAlchemy!=2.0.36,<2.1,>=2.0
Requires-Dist: sqlitedict
Requires-Dist: starlette
Requires-Dist: svgwrite
Requires-Dist: typing-extensions
Requires-Dist: WebOb>=1.8.9
Requires-Dist: Whoosh
Dynamic: license-file
